{
    "owner": "ROM",
    "controller": "ROM",
    "add_core": "ROM",
    "population_total": {
        "amount": 431389,
        "template": 50,
        "populations": {
            "farmers": 0.80748,
            "labourers": 0.0616,
            "craftsmen": 0.0,
            "clerks": 0.0,
            "aristocrats": 0.00402,
            "artisans": 0.03793,
            "bureaucrats": 0.00426,
            "capitalists": 0.0361,
            "clergymen": 0.0182,
            "officers": 0.00595,
            "slaves": 0.0,
            "soldiers": 0.02446
        },
        "cultures": {
            "romanian": 0.96,
            "roma": 0.04
        },
        "religions": {
            "orthodox": 0.95752,
            "atheist": 0.04248
        }
    },
    "good": "grain",
    "buildings": [
        {
            "name": "railway",
            "size": 5
        }
    ],
    "terrain": "mountains"
}