{
    "add_core": "GRE",
    "owner": "GRE",
    "controller": "GRE",
    "population_total": {
        "amount": 327487,
        "template": 63,
        "populations": {
            "farmers": 0.26831,
            "labourers": 0.09027,
            "craftsmen": 0.3646,
            "clerks": 0.15625,
            "aristocrats": 0.00422,
            "artisans": 0.03229,
            "bureaucrats": 0.00472,
            "capitalists": 0.03243,
            "clergymen": 0.0168,
            "officers": 0.00592,
            "slaves": 0.0,
            "soldiers": 0.02419
        },
        "cultures": {
            "greek": 1.0
        },
        "religions": {
            "orthodox": 0.94024,
            "atheist": 0.05976
        }
    },
    "good": "fish",
    "buildings": [
        {
            "name": "railway",
            "size": 5
        },
        {
            "name": "naval_base",
            "size": 1
        }
    ],
    "terrain": "hills",
    "economy_buildings": [
        {
            "name": "ammunition_factory",
            "size": 5
        },
        {
            "name": "weaponry_factory",
            "size": 5
        }
    ]
}