{
  "country": "DMN",
  "leaders": {
    "12692": {
      "name": "Kyle Yates",
      "skill": 0,
      "force_type": "land",
      "trait": "common"
    },
    "12693": {
      "name": "Daniel Richardson",
      "skill": 0,
      "force_type": "land",
      "trait": "common"
    },
    "12694": {
      "name": "Shane Kirk",
      "skill": 0,
      "force_type": "land",
      "trait": "common"
    },
    "12695": {
      "name": "Shawn Riley",
      "skill": 0,
      "force_type": "land",
      "trait": "common"
    },
    "12696": {
      "name": "Cody Bradshaw",
      "skill": 0,
      "force_type": "land",
      "trait": "common"
    },
    "12697": {
      "name": "Shane Short",
      "skill": 0,
      "force_type": "land",
      "trait": "common"
    },
    "12698": {
      "name": "Scott Power",
      "skill": 0,
      "force_type": "land",
      "trait": "common"
    },
    "12699": {
      "name": "Miguel Johnson",
      "skill": 0,
      "force_type": "land",
      "trait": "logistics_wizard"
    },
    "12700": {
      "name": "Brian Khan",
      "skill": 0,
      "force_type": "land",
      "trait": "common"
    },
    "12701": {
      "name": "Jesse Whittaker",
      "skill": 0,
      "force_type": "land",
      "trait": "common"
    },
    "12702": {
      "name": "Corey Barrett",
      "skill": 0,
      "force_type": "land",
      "trait": "common"
    },
    "12703": {
      "name": "Tyler Wells",
      "skill": 0,
      "force_type": "land",
      "trait": "defensive_doctrine"
    },
    "12704": {
      "name": "Kyle Thompson",
      "skill": 0,
      "force_type": "land",
      "trait": "common"
    },
    "12705": {
      "name": "Vincent Herbert",
      "skill": 0,
      "force_type": "land",
      "trait": "defensive_doctrine"
    },
    "12706": {
      "name": "Andrew Barrett",
      "skill": 0,
      "force_type": "land",
      "trait": "commando"
    },
    "12707": {
      "name": "Adrian Bradley",
      "skill": 0,
      "force_type": "land",
      "trait": "commando"
    },
    "12708": {
      "name": "Nathan Todd",
      "skill": 0,
      "force_type": "land",
      "trait": "logistics_wizard"
    },
    "12709": {
      "name": "Joshua Blake",
      "skill": 0,
      "force_type": "land",
      "trait": "common"
    },
    "12710": {
      "name": "Adrian Birch",
      "skill": 0,
      "force_type": "land",
      "trait": "common"
    },
    "12711": {
      "name": "Alexander Ferguson",
      "skill": 0,
      "force_type": "land",
      "trait": "common"
    },
    "12712": {
      "name": "Daniel Murray",
      "skill": 0,
      "force_type": "land",
      "trait": "common"
    },
    "12713": {
      "name": "Jeremy Harris",
      "skill": 0,
      "force_type": "land",
      "trait": "common"
    },
    "12714": {
      "name": "Nicholas Winter",
      "skill": 0,
      "force_type": "land",
      "trait": "common"
    },
    "12715": {
      "name": "Travis Sinclair",
      "skill": 0,
      "force_type": "land",
      "trait": "common"
    },
    "12716": {
      "name": "Travis Charlton",
      "skill": 0,
      "force_type": "land",
      "trait": "common"
    },
    "12717": {
      "name": "Paul McKenzie",
      "skill": 0,
      "force_type": "land",
      "trait": "common"
    },
    "12718": {
      "name": "Phillip Giles",
      "skill": 0,
      "force_type": "land",
      "trait": "commando"
    },
    "12719": {
      "name": "Jesse Barrett",
      "skill": 0,
      "force_type": "land",
      "trait": "common"
    },
    "12720": {
      "name": "James Gilbert",
      "skill": 0,
      "force_type": "land",
      "trait": "common"
    },
    "12721": {
      "name": "Phillip Read",
      "skill": 0,
      "force_type": "land",
      "trait": "common"
    },
    "12722": {
      "name": "Miguel Spencer",
      "skill": 0,
      "force_type": "land",
      "trait": "panzer_leader"
    },
    "12723": {
      "name": "Cory Potter",
      "skill": 0,
      "force_type": "land",
      "trait": "common"
    },
    "12724": {
      "name": "Adam Wade",
      "skill": 0,
      "force_type": "land",
      "trait": "common"
    },
    "12725": {
      "name": "Scott Stewart",
      "skill": 0,
      "force_type": "land",
      "trait": "common"
    },
    "12726": {
      "name": "Samuel Hammond",
      "skill": 0,
      "force_type": "land",
      "trait": "commando"
    },
    "12727": {
      "name": "Justin Swift",
      "skill": 0,
      "force_type": "land",
      "trait": "common"
    },
    "12728": {
      "name": "William Francis",
      "skill": 0,
      "force_type": "land",
      "trait": "common"
    },
    "12729": {
      "name": "Joshua Sutton",
      "skill": 0,
      "force_type": "land",
      "trait": "common"
    },
    "12730": {
      "name": "Jacob Newman",
      "skill": 0,
      "force_type": "land",
      "trait": "logistics_wizard"
    },
    "12731": {
      "name": "Sean Kent",
      "skill": 0,
      "force_type": "land",
      "trait": "offensive_doctrine"
    },
    "12732": {
      "name": "Zachary Alexander",
      "skill": 0,
      "force_type": "land",
      "trait": "commando"
    },
    "12733": {
      "name": "Bryan Edwards",
      "skill": 0,
      "force_type": "land",
      "trait": "common"
    },
    "12734": {
      "name": "Victor Curtis",
      "skill": 0,
      "force_type": "land",
      "trait": "commando"
    },
    "12735": {
      "name": "Phillip Russell",
      "skill": 0,
      "force_type": "land",
      "trait": "common"
    },
    "12736": {
      "name": "Gabriel Alexander",
      "skill": 0,
      "force_type": "land",
      "trait": "trickster"
    },
    "12737": {
      "name": "Aaron Murray",
      "skill": 0,
      "force_type": "land",
      "trait": "common"
    },
    "12738": {
      "name": "Richard Dixon",
      "skill": 0,
      "force_type": "land",
      "trait": "logistics_wizard"
    },
    "12739": {
      "name": "Chad Andrews",
      "skill": 0,
      "force_type": "land",
      "trait": "logistics_wizard"
    },
    "12740": {
      "name": "Robert Kent",
      "skill": 0,
      "force_type": "land",
      "trait": "common"
    },
    "12741": {
      "name": "Paul Quinn",
      "skill": 0,
      "force_type": "land",
      "trait": "common"
    },
    "12742": {
      "name": "Erik Tomlinson",
      "skill": 0,
      "force_type": "land",
      "trait": "common"
    },
    "12743": {
      "name": "Peter Lucas",
      "skill": 0,
      "force_type": "sea",
      "trait": "common"
    },
    "12744": {
      "name": "Evan Thomson",
      "skill": 0,
      "force_type": "sea",
      "trait": "superior_tactician"
    },
    "12745": {
      "name": "Kevin Wilkins",
      "skill": 0,
      "force_type": "sea",
      "trait": "common"
    },
    "12746": {
      "name": "Luis Thorpe",
      "skill": 0,
      "force_type": "sea",
      "trait": "common"
    },
    "12747": {
      "name": "Bryan Dickinson",
      "skill": 0,
      "force_type": "sea",
      "trait": "common"
    },
    "12748": {
      "name": "Jeffrey Kent",
      "skill": 0,
      "force_type": "sea",
      "trait": "common"
    },
    "12749": {
      "name": "Jeremy Shaw",
      "skill": 0,
      "force_type": "sea",
      "trait": "superior_tactician"
    },
    "12750": {
      "name": "Kevin Wyatt",
      "skill": 0,
      "force_type": "sea",
      "trait": "spotter"
    },
    "12751": {
      "name": "David Leonard",
      "skill": 0,
      "force_type": "sea",
      "trait": "common"
    },
    "12752": {
      "name": "Bradley Gibbons",
      "skill": 0,
      "force_type": "sea",
      "trait": "common"
    },
    "12753": {
      "name": "Andrew Gregory",
      "skill": 0,
      "force_type": "sea",
      "trait": "common"
    },
    "12754": {
      "name": "Jeremy Rice",
      "skill": 0,
      "force_type": "sea",
      "trait": "common"
    },
    "12755": {
      "name": "Jared Davey",
      "skill": 0,
      "force_type": "sea",
      "trait": "common"
    },
    "12756": {
      "name": "Robert Nixon",
      "skill": 0,
      "force_type": "sea",
      "trait": "common"
    },
    "12757": {
      "name": "Kenneth Goodwin",
      "skill": 0,
      "force_type": "sea",
      "trait": "common"
    },
    "12758": {
      "name": "Derek Clark",
      "skill": 0,
      "force_type": "sea",
      "trait": "common"
    },
    "12759": {
      "name": "Benjamin Whittaker",
      "skill": 0,
      "force_type": "sea",
      "trait": "superior_tactician"
    },
    "12760": {
      "name": "Luis Leach",
      "skill": 0,
      "force_type": "sea",
      "trait": "superior_tactician"
    },
    "12761": {
      "name": "Peter Goddard",
      "skill": 0,
      "force_type": "sea",
      "trait": "common"
    },
    "12762": {
      "name": "Casey Howard",
      "skill": 0,
      "force_type": "sea",
      "trait": "common"
    },
    "12763": {
      "name": "Scott Thomson",
      "skill": 0,
      "force_type": "sea",
      "trait": "common"
    },
    "12764": {
      "name": "Kevin Matthews",
      "skill": 0,
      "force_type": "sea",
      "trait": "common"
    },
    "12765": {
      "name": "William Russell",
      "skill": 0,
      "force_type": "sea",
      "trait": "common"
    },
    "12766": {
      "name": "Robert Goddard",
      "skill": 0,
      "force_type": "sea",
      "trait": "common"
    },
    "12767": {
      "name": "Derek Bentley",
      "skill": 0,
      "force_type": "sea",
      "trait": "common"
    },
    "12768": {
      "name": "Thomas Wilkinson",
      "skill": 0,
      "force_type": "sea",
      "trait": "common"
    },
    "12769": {
      "name": "Jonathan Middleton",
      "skill": 0,
      "force_type": "sea",
      "trait": "common"
    },
    "12770": {
      "name": "Nicholas Stevenson",
      "skill": 0,
      "force_type": "sea",
      "trait": "common"
    },
    "12771": {
      "name": "Thomas Stevenson",
      "skill": 0,
      "force_type": "sea",
      "trait": "superior_tactician"
    },
    "12772": {
      "name": "Vincent Walker",
      "skill": 0,
      "force_type": "sea",
      "trait": "superior_tactician"
    },
    "12773": {
      "name": "Carlos Howarth",
      "skill": 0,
      "force_type": "sea",
      "trait": "common"
    },
    "12774": {
      "name": "Benjamin Shaw",
      "skill": 0,
      "force_type": "sea",
      "trait": "common"
    },
    "12775": {
      "name": "Peter Graham",
      "skill": 0,
      "force_type": "sea",
      "trait": "common"
    },
    "12776": {
      "name": "Luis Turner",
      "skill": 0,
      "force_type": "air",
      "trait": "common"
    },
    "12777": {
      "name": "Christopher Morley",
      "skill": 0,
      "force_type": "air",
      "trait": "common"
    },
    "12778": {
      "name": "Kevin Spencer",
      "skill": 0,
      "force_type": "air",
      "trait": "common"
    },
    "12779": {
      "name": "Matthew Daniels",
      "skill": 0,
      "force_type": "air",
      "trait": "common"
    },
    "12780": {
      "name": "Luis Read",
      "skill": 0,
      "force_type": "air",
      "trait": "common"
    },
    "12781": {
      "name": "Jesse Morgan",
      "skill": 0,
      "force_type": "air",
      "trait": "common"
    },
    "12782": {
      "name": "Christopher Hodgson",
      "skill": 0,
      "force_type": "air",
      "trait": "common"
    },
    "12783": {
      "name": "Christian Dunn",
      "skill": 0,
      "force_type": "air",
      "trait": "superior_air_tactician"
    },
    "12784": {
      "name": "Shawn Fowler",
      "skill": 0,
      "force_type": "air",
      "trait": "superior_air_tactician"
    },
    "12785": {
      "name": "Jared Gibbons",
      "skill": 0,
      "force_type": "air",
      "trait": "superior_air_tactician"
    },
    "12786": {
      "name": "Trevor Leonard",
      "skill": 0,
      "force_type": "air",
      "trait": "common"
    },
    "12787": {
      "name": "Evan Byrne",
      "skill": 0,
      "force_type": "air",
      "trait": "superior_air_tactician"
    },
    "12788": {
      "name": "Kyle Watson",
      "skill": 0,
      "force_type": "air",
      "trait": "common"
    },
    "12789": {
      "name": "Jonathan Brown",
      "skill": 0,
      "force_type": "air",
      "trait": "common"
    },
    "12790": {
      "name": "John Walsh",
      "skill": 0,
      "force_type": "air",
      "trait": "common"
    },
    "12791": {
      "name": "George Hicks",
      "skill": 0,
      "force_type": "air",
      "trait": "common"
    },
    "12792": {
      "name": "Miguel Herbert",
      "skill": 0,
      "force_type": "air",
      "trait": "common"
    },
    "12793": {
      "name": "Samuel Farrell",
      "skill": 0,
      "force_type": "air",
      "trait": "common"
    },
    "12794": {
      "name": "Kyle Daly",
      "skill": 0,
      "force_type": "air",
      "trait": "tank_buster"
    },
    "12795": {
      "name": "Zachary Smart",
      "skill": 0,
      "force_type": "air",
      "trait": "common"
    },
    "12796": {
      "name": "Carlos Kirk",
      "skill": 0,
      "force_type": "air",
      "trait": "common"
    },
    "12797": {
      "name": "Jared Reynolds",
      "skill": 0,
      "force_type": "air",
      "trait": "superior_air_tactician"
    },
    "12798": {
      "name": "Zachary Moore",
      "skill": 0,
      "force_type": "air",
      "trait": "superior_air_tactician"
    },
    "12799": {
      "name": "Erik Wyatt",
      "skill": 0,
      "force_type": "air",
      "trait": "carpet_bomber"
    },
    "12800": {
      "name": "Steven Sims",
      "skill": 0,
      "force_type": "air",
      "trait": "common"
    },
    "12801": {
      "name": "Phillip Gough",
      "skill": 0,
      "force_type": "air",
      "trait": "common"
    },
    "12802": {
      "name": "David Flynn",
      "skill": 0,
      "force_type": "air",
      "trait": "fleet_destroyer"
    },
    "12803": {
      "name": "Jordan Riley",
      "skill": 0,
      "force_type": "air",
      "trait": "common"
    },
    "12804": {
      "name": "Ryan Rice",
      "skill": 0,
      "force_type": "air",
      "trait": "common"
    },
    "12805": {
      "name": "Brett Donnelly",
      "skill": 0,
      "force_type": "air",
      "trait": "fleet_destroyer"
    },
    "12806": {
      "name": "Garrett Elliott",
      "skill": 0,
      "force_type": "air",
      "trait": "common"
    },
    "12807": {
      "name": "Raymond Fox",
      "skill": 0,
      "force_type": "air",
      "trait": "common"
    },
    "12808": {
      "name": "Samuel Ali",
      "skill": 0,
      "force_type": "air",
      "trait": "common"
    },
    "12809": {
      "name": "Luis Wyatt",
      "skill": 0,
      "force_type": "air",
      "trait": "common"
    },
    "12810": {
      "name": "William Knowles",
      "skill": 0,
      "force_type": "air",
      "trait": "common"
    }
  }
}