{
  "country": "GRT",
  "leaders": {
    "17942": {
      "name": "Cameron Joyce",
      "skill": 4,
      "force_type": "land",
      "trait": "common"
    },
    "17943": {
      "name": "Raymond Potts",
      "skill": 2,
      "force_type": "land",
      "trait": "common"
    },
    "17944": {
      "name": "Luis Morley",
      "skill": 0,
      "force_type": "land",
      "trait": "common"
    },
    "17945": {
      "name": "Chad Morgan",
      "skill": 1,
      "force_type": "land",
      "trait": "common"
    },
    "17946": {
      "name": "Carlos Charlton",
      "skill": 0,
      "force_type": "land",
      "trait": "common"
    },
    "17947": {
      "name": "Adam Lewis",
      "skill": 3,
      "force_type": "land",
      "trait": "common"
    },
    "17948": {
      "name": "Edward Fisher",
      "skill": 0,
      "force_type": "land",
      "trait": "common"
    },
    "17949": {
      "name": "Travis Robinson",
      "skill": 2,
      "force_type": "land",
      "trait": "common"
    },
    "17950": {
      "name": "Vincent Browne",
      "skill": 1,
      "force_type": "land",
      "trait": "common"
    },
    "17951": {
      "name": "Cody Stone",
      "skill": 2,
      "force_type": "land",
      "trait": "common"
    },
    "17952": {
      "name": "Jacob Bradley",
      "skill": 0,
      "force_type": "land",
      "trait": "common"
    },
    "17953": {
      "name": "Shane Cooke",
      "skill": 0,
      "force_type": "land",
      "trait": "panzer_leader"
    },
    "17954": {
      "name": "Patrick Fox",
      "skill": 1,
      "force_type": "land",
      "trait": "common"
    },
    "17955": {
      "name": "Martin Green",
      "skill": 1,
      "force_type": "land",
      "trait": "common"
    },
    "17956": {
      "name": "Stephen Stone",
      "skill": 0,
      "force_type": "land",
      "trait": "common"
    },
    "17957": {
      "name": "Sean King",
      "skill": 2,
      "force_type": "land",
      "trait": "common"
    },
    "17958": {
      "name": "Phillip Mills",
      "skill": 1,
      "force_type": "land",
      "trait": "common"
    },
    "17959": {
      "name": "James Wilkinson",
      "skill": 2,
      "force_type": "land",
      "trait": "logistics_wizard"
    },
    "17960": {
      "name": "Jeffrey Connolly",
      "skill": 1,
      "force_type": "land",
      "trait": "common"
    },
    "17961": {
      "name": "Corey Murphy",
      "skill": 2,
      "force_type": "land",
      "trait": "common"
    },
    "17962": {
      "name": "John Cole",
      "skill": 0,
      "force_type": "land",
      "trait": "common"
    },
    "17963": {
      "name": "Chad Knowles",
      "skill": 1,
      "force_type": "land",
      "trait": "defensive_doctrine"
    },
    "17964": {
      "name": "Stephen Houghton",
      "skill": 0,
      "force_type": "land",
      "trait": "defensive_doctrine"
    },
    "17965": {
      "name": "Paul Cook",
      "skill": 0,
      "force_type": "land",
      "trait": "common"
    },
    "17966": {
      "name": "Martin Barnett",
      "skill": 2,
      "force_type": "land",
      "trait": "common"
    },
    "17967": {
      "name": "John Fleming",
      "skill": 0,
      "force_type": "land",
      "trait": "common"
    },
    "17968": {
      "name": "Shane McLean",
      "skill": 0,
      "force_type": "land",
      "trait": "offensive_doctrine"
    },
    "17969": {
      "name": "Erik Gould",
      "skill": 0,
      "force_type": "land",
      "trait": "common"
    },
    "17970": {
      "name": "Spencer Lyons",
      "skill": 4,
      "force_type": "land",
      "trait": "common"
    },
    "17971": {
      "name": "Ian Thorpe",
      "skill": 0,
      "force_type": "land",
      "trait": "engineer"
    },
    "17972": {
      "name": "Scott Wood",
      "skill": 0,
      "force_type": "land",
      "trait": "defensive_doctrine"
    },
    "17973": {
      "name": "Dustin Reid",
      "skill": 3,
      "force_type": "land",
      "trait": "trickster"
    },
    "17974": {
      "name": "Jeremy Burgess",
      "skill": 1,
      "force_type": "land",
      "trait": "common"
    },
    "17975": {
      "name": "Carlos Harper",
      "skill": 0,
      "force_type": "land",
      "trait": "common"
    },
    "17976": {
      "name": "Ryan Marsh",
      "skill": 0,
      "force_type": "land",
      "trait": "offensive_doctrine"
    },
    "17977": {
      "name": "Jason Coles",
      "skill": 0,
      "force_type": "land",
      "trait": "common"
    },
    "17978": {
      "name": "Brett Scott",
      "skill": 1,
      "force_type": "land",
      "trait": "common"
    },
    "17979": {
      "name": "Alexander Bruce",
      "skill": 1,
      "force_type": "land",
      "trait": "offensive_doctrine"
    },
    "17980": {
      "name": "Aaron Foster",
      "skill": 1,
      "force_type": "land",
      "trait": "offensive_doctrine"
    },
    "17981": {
      "name": "Robert Turnbull",
      "skill": 0,
      "force_type": "land",
      "trait": "common"
    },
    "17982": {
      "name": "Matthew Richardson",
      "skill": 2,
      "force_type": "land",
      "trait": "common"
    },
    "17983": {
      "name": "Nicholas White",
      "skill": 2,
      "force_type": "land",
      "trait": "engineer"
    },
    "17984": {
      "name": "Christopher Hughes",
      "skill": 1,
      "force_type": "land",
      "trait": "common"
    },
    "17985": {
      "name": "Raymond Macdonald",
      "skill": 1,
      "force_type": "land",
      "trait": "common"
    },
    "17986": {
      "name": "Jason Evans",
      "skill": 0,
      "force_type": "land",
      "trait": "common"
    },
    "17987": {
      "name": "Jordan Gough",
      "skill": 2,
      "force_type": "land",
      "trait": "common"
    },
    "17988": {
      "name": "Steven Browne",
      "skill": 2,
      "force_type": "land",
      "trait": "common"
    },
    "17989": {
      "name": "Francisco Sinclair",
      "skill": 1,
      "force_type": "land",
      "trait": "common"
    },
    "17990": {
      "name": "Evan Murray",
      "skill": 2,
      "force_type": "land",
      "trait": "engineer"
    },
    "17991": {
      "name": "Christopher Burgess",
      "skill": 0,
      "force_type": "land",
      "trait": "offensive_doctrine"
    },
    "17992": {
      "name": "Jared Fuller",
      "skill": 2,
      "force_type": "land",
      "trait": "logistics_wizard"
    },
    "17993": {
      "name": "Timothy O'Sullivan",
      "skill": 1,
      "force_type": "sea",
      "trait": "common"
    },
    "17994": {
      "name": "Dustin Herbert",
      "skill": 3,
      "force_type": "sea",
      "trait": "blockade_runner"
    },
    "17995": {
      "name": "Jacob West",
      "skill": 0,
      "force_type": "sea",
      "trait": "common"
    },
    "17996": {
      "name": "Erik Little",
      "skill": 4,
      "force_type": "sea",
      "trait": "common"
    },
    "17997": {
      "name": "Joseph Power",
      "skill": 0,
      "force_type": "sea",
      "trait": "superior_tactician"
    },
    "17998": {
      "name": "Miguel Cooper",
      "skill": 2,
      "force_type": "sea",
      "trait": "common"
    },
    "17999": {
      "name": "Ian Birch",
      "skill": 0,
      "force_type": "sea",
      "trait": "blockade_runner"
    },
    "18000": {
      "name": "Jordan Blake",
      "skill": 3,
      "force_type": "sea",
      "trait": "common"
    },
    "18001": {
      "name": "John Myers",
      "skill": 0,
      "force_type": "sea",
      "trait": "common"
    },
    "18002": {
      "name": "John Booth",
      "skill": 1,
      "force_type": "sea",
      "trait": "superior_tactician"
    },
    "18003": {
      "name": "Raymond Carroll",
      "skill": 3,
      "force_type": "sea",
      "trait": "common"
    },
    "18004": {
      "name": "Samuel O'Connor",
      "skill": 2,
      "force_type": "sea",
      "trait": "superior_tactician"
    },
    "18005": {
      "name": "Jared Cooper",
      "skill": 0,
      "force_type": "sea",
      "trait": "common"
    },
    "18006": {
      "name": "Charles Gregory",
      "skill": 1,
      "force_type": "sea",
      "trait": "common"
    },
    "18007": {
      "name": "Daniel Wood",
      "skill": 2,
      "force_type": "sea",
      "trait": "common"
    },
    "18008": {
      "name": "Martin Walsh",
      "skill": 0,
      "force_type": "sea",
      "trait": "common"
    },
    "18009": {
      "name": "Kevin Oliver",
      "skill": 4,
      "force_type": "sea",
      "trait": "common"
    },
    "18010": {
      "name": "Timothy Storey",
      "skill": 1,
      "force_type": "sea",
      "trait": "superior_tactician"
    },
    "18011": {
      "name": "Alex Gilbert",
      "skill": 3,
      "force_type": "sea",
      "trait": "common"
    },
    "18012": {
      "name": "Jonathan Hooper",
      "skill": 0,
      "force_type": "sea",
      "trait": "common"
    },
    "18013": {
      "name": "Jesse Whitehouse",
      "skill": 1,
      "force_type": "sea",
      "trait": "superior_tactician"
    },
    "18014": {
      "name": "Cody Vincent",
      "skill": 1,
      "force_type": "sea",
      "trait": "spotter"
    },
    "18015": {
      "name": "James Hamilton",
      "skill": 1,
      "force_type": "sea",
      "trait": "common"
    },
    "18016": {
      "name": "Aaron Blake",
      "skill": 1,
      "force_type": "sea",
      "trait": "blockade_runner"
    },
    "18017": {
      "name": "Francisco Shaw",
      "skill": 2,
      "force_type": "sea",
      "trait": "common"
    },
    "18018": {
      "name": "Samuel Brown",
      "skill": 1,
      "force_type": "sea",
      "trait": "common"
    },
    "18019": {
      "name": "David Ellis",
      "skill": 1,
      "force_type": "sea",
      "trait": "common"
    },
    "18020": {
      "name": "James Swift",
      "skill": 1,
      "force_type": "sea",
      "trait": "common"
    },
    "18021": {
      "name": "Mark Summers",
      "skill": 0,
      "force_type": "sea",
      "trait": "superior_tactician"
    },
    "18022": {
      "name": "Edward Holland",
      "skill": 3,
      "force_type": "sea",
      "trait": "common"
    },
    "18023": {
      "name": "Gregory Carroll",
      "skill": 1,
      "force_type": "sea",
      "trait": "common"
    },
    "18024": {
      "name": "Eric Rogers",
      "skill": 0,
      "force_type": "sea",
      "trait": "common"
    },
    "18025": {
      "name": "Raymond Hughes",
      "skill": 3,
      "force_type": "air",
      "trait": "common"
    },
    "18026": {
      "name": "Derek Patel",
      "skill": 2,
      "force_type": "air",
      "trait": "common"
    },
    "18027": {
      "name": "Paul Kennedy",
      "skill": 2,
      "force_type": "air",
      "trait": "tank_buster"
    },
    "18028": {
      "name": "Cody Stevens",
      "skill": 1,
      "force_type": "air",
      "trait": "common"
    },
    "18029": {
      "name": "Kevin Carroll",
      "skill": 1,
      "force_type": "air",
      "trait": "common"
    },
    "18030": {
      "name": "Victor Dobson",
      "skill": 1,
      "force_type": "air",
      "trait": "superior_air_tactician"
    },
    "18031": {
      "name": "Alexander Gilbert",
      "skill": 0,
      "force_type": "air",
      "trait": "common"
    },
    "18032": {
      "name": "William Alexander",
      "skill": 0,
      "force_type": "air",
      "trait": "common"
    },
    "18033": {
      "name": "Jeffrey Holloway",
      "skill": 1,
      "force_type": "air",
      "trait": "common"
    },
    "18034": {
      "name": "Samuel Allen",
      "skill": 2,
      "force_type": "air",
      "trait": "common"
    },
    "18035": {
      "name": "Kenneth Cooke",
      "skill": 2,
      "force_type": "air",
      "trait": "common"
    },
    "18036": {
      "name": "Cody Lambert",
      "skill": 1,
      "force_type": "air",
      "trait": "common"
    },
    "18037": {
      "name": "Thomas Ellis",
      "skill": 3,
      "force_type": "air",
      "trait": "common"
    },
    "18038": {
      "name": "Shawn George",
      "skill": 1,
      "force_type": "air",
      "trait": "common"
    },
    "18039": {
      "name": "Mark Rees",
      "skill": 2,
      "force_type": "air",
      "trait": "tank_buster"
    },
    "18040": {
      "name": "Adam Summers",
      "skill": 0,
      "force_type": "air",
      "trait": "common"
    },
    "18041": {
      "name": "Aaron Macdonald",
      "skill": 1,
      "force_type": "air",
      "trait": "superior_air_tactician"
    },
    "18042": {
      "name": "Nathan Davison",
      "skill": 0,
      "force_type": "air",
      "trait": "common"
    },
    "18043": {
      "name": "Richard Marsden",
      "skill": 1,
      "force_type": "air",
      "trait": "common"
    },
    "18044": {
      "name": "Robert O'Brien",
      "skill": 0,
      "force_type": "air",
      "trait": "common"
    },
    "18045": {
      "name": "Shawn Cooke",
      "skill": 1,
      "force_type": "air",
      "trait": "common"
    },
    "18046": {
      "name": "Bryan Wyatt",
      "skill": 0,
      "force_type": "air",
      "trait": "common"
    },
    "18047": {
      "name": "Scott Patel",
      "skill": 0,
      "force_type": "air",
      "trait": "fleet_destroyer"
    },
    "18048": {
      "name": "Carlos Leach",
      "skill": 0,
      "force_type": "air",
      "trait": "common"
    },
    "18049": {
      "name": "James West",
      "skill": 5,
      "force_type": "air",
      "trait": "superior_air_tactician"
    },
    "18050": {
      "name": "Vincent Baxter",
      "skill": 0,
      "force_type": "air",
      "trait": "common"
    },
    "18051": {
      "name": "Victor Brown",
      "skill": 1,
      "force_type": "air",
      "trait": "common"
    },
    "18052": {
      "name": "Brian Parry",
      "skill": 1,
      "force_type": "air",
      "trait": "superior_air_tactician"
    },
    "18053": {
      "name": "Kenneth Walsh",
      "skill": 1,
      "force_type": "air",
      "trait": "common"
    },
    "18054": {
      "name": "Casey Flynn",
      "skill": 1,
      "force_type": "air",
      "trait": "superior_air_tactician"
    }
  }
}