{
    "country": "MLD",
    "leaders": [
        {
            "name": "Sandeep Fernandes",
            "skill": 0,
            "force_type": "land",
            "trait": "common"
        },
        {
            "name": "Mayank Banerjee",
            "skill": 0,
            "force_type": "land",
            "trait": "common"
        },
        {
            "name": "Nitin Bisht",
            "skill": 0,
            "force_type": "land",
            "trait": "common"
        },
        {
            "name": "Shishira Verma",
            "skill": 0,
            "force_type": "land",
            "trait": "common"
        },
        {
            "name": "Krishnan Patel",
            "skill": 0,
            "force_type": "land",
            "trait": "common"
        },
        {
            "name": "Nirav Thakur",
            "skill": 0,
            "force_type": "land",
            "trait": "common"
        },
        {
            "name": "Nadeem Rizvi",
            "skill": 0,
            "force_type": "land",
            "trait": "common"
        },
        {
            "name": "Gurunath Baghel",
            "skill": 0,
            "force_type": "land",
            "trait": "commando"
        },
        {
            "name": "Jaipal Trivedi",
            "skill": 0,
            "force_type": "land",
            "trait": "defensive_doctrine"
        },
        {
            "name": "Hitesh Arora",
            "skill": 0,
            "force_type": "land",
            "trait": "commando"
        },
        {
            "name": "Surinder Patil",
            "skill": 0,
            "force_type": "land",
            "trait": "common"
        },
        {
            "name": "Ashoka Reddy",
            "skill": 0,
            "force_type": "land",
            "trait": "common"
        },
        {
            "name": "Devesh Sharma",
            "skill": 0,
            "force_type": "land",
            "trait": "commando"
        },
        {
            "name": "Wasim Srivastava",
            "skill": 0,
            "force_type": "land",
            "trait": "common"
        },
        {
            "name": "Nilesh Sharma",
            "skill": 0,
            "force_type": "land",
            "trait": "common"
        },
        {
            "name": "Binu Brar",
            "skill": 0,
            "force_type": "land",
            "trait": "common"
        },
        {
            "name": "Srinivas Rana",
            "skill": 0,
            "force_type": "land",
            "trait": "common"
        },
        {
            "name": "Rajinder Mitra",
            "skill": 0,
            "force_type": "land",
            "trait": "common"
        },
        {
            "name": "Rohit Kamat",
            "skill": 0,
            "force_type": "land",
            "trait": "common"
        },
        {
            "name": "Soumitra Shaikh",
            "skill": 0,
            "force_type": "land",
            "trait": "common"
        },
        {
            "name": "Suresh Jha",
            "skill": 0,
            "force_type": "land",
            "trait": "defensive_doctrine"
        },
        {
            "name": "Bijan Sayyed",
            "skill": 0,
            "force_type": "land",
            "trait": "common"
        },
        {
            "name": "Shahbaz Bisht",
            "skill": 0,
            "force_type": "land",
            "trait": "commando"
        },
        {
            "name": "Ishana Poonia",
            "skill": 0,
            "force_type": "land",
            "trait": "common"
        },
        {
            "name": "Abhay Sandhu",
            "skill": 0,
            "force_type": "land",
            "trait": "common"
        },
        {
            "name": "Bijan Jain",
            "skill": 0,
            "force_type": "land",
            "trait": "common"
        },
        {
            "name": "Abhinav Holkar",
            "skill": 0,
            "force_type": "land",
            "trait": "common"
        },
        {
            "name": "Shubhendu Dwivedi",
            "skill": 0,
            "force_type": "land",
            "trait": "logistics_wizard"
        },
        {
            "name": "Yash Roy",
            "skill": 0,
            "force_type": "land",
            "trait": "common"
        },
        {
            "name": "Shubhendu Tomar",
            "skill": 0,
            "force_type": "land",
            "trait": "common"
        },
        {
            "name": "Anil Prasad",
            "skill": 0,
            "force_type": "land",
            "trait": "defensive_doctrine"
        },
        {
            "name": "Wasim Roy",
            "skill": 0,
            "force_type": "land",
            "trait": "common"
        },
        {
            "name": "Ishana Swamy",
            "skill": 0,
            "force_type": "land",
            "trait": "defensive_doctrine"
        },
        {
            "name": "Ajit Pal",
            "skill": 0,
            "force_type": "land",
            "trait": "offensive_doctrine"
        },
        {
            "name": "Ranbir Gowda",
            "skill": 0,
            "force_type": "land",
            "trait": "common"
        },
        {
            "name": "Dinesh Nayak",
            "skill": 0,
            "force_type": "land",
            "trait": "common"
        },
        {
            "name": "Shailendra Pradhan",
            "skill": 0,
            "force_type": "land",
            "trait": "common"
        },
        {
            "name": "Nihal Bhatt",
            "skill": 0,
            "force_type": "land",
            "trait": "common"
        },
        {
            "name": "Sunil Mishra",
            "skill": 0,
            "force_type": "land",
            "trait": "logistics_wizard"
        },
        {
            "name": "Yash Uniyal",
            "skill": 0,
            "force_type": "land",
            "trait": "common"
        },
        {
            "name": "Sekar Pal",
            "skill": 0,
            "force_type": "land",
            "trait": "common"
        },
        {
            "name": "Kartika Parmar",
            "skill": 0,
            "force_type": "land",
            "trait": "common"
        },
        {
            "name": "Arun Thakur",
            "skill": 0,
            "force_type": "land",
            "trait": "commando"
        },
        {
            "name": "Sunil Sarkar",
            "skill": 0,
            "force_type": "land",
            "trait": "common"
        },
        {
            "name": "Mahendra Sharma",
            "skill": 0,
            "force_type": "land",
            "trait": "common"
        },
        {
            "name": "Gotama Bhatnagar",
            "skill": 0,
            "force_type": "land",
            "trait": "common"
        },
        {
            "name": "Abhinav Jadhav",
            "skill": 0,
            "force_type": "land",
            "trait": "common"
        },
        {
            "name": "Hitesh Bhattacharya",
            "skill": 0,
            "force_type": "land",
            "trait": "common"
        },
        {
            "name": "Smeet Bhosle",
            "skill": 0,
            "force_type": "land",
            "trait": "common"
        },
        {
            "name": "Aniruddha Dwivedi",
            "skill": 0,
            "force_type": "land",
            "trait": "commando"
        },
        {
            "name": "Rajiv Naqvi",
            "skill": 0,
            "force_type": "land",
            "trait": "common"
        },
        {
            "name": "Vinay Sayyed",
            "skill": 0,
            "force_type": "sea",
            "trait": "common"
        },
        {
            "name": "Munish Roy",
            "skill": 0,
            "force_type": "sea",
            "trait": "common"
        },
        {
            "name": "Gurunath Bargal",
            "skill": 0,
            "force_type": "sea",
            "trait": "common"
        },
        {
            "name": "Ranbir Fernandes",
            "skill": 0,
            "force_type": "sea",
            "trait": "common"
        },
        {
            "name": "Mahboob Holkar",
            "skill": 0,
            "force_type": "sea",
            "trait": "common"
        },
        {
            "name": "Shishir Bhatt",
            "skill": 0,
            "force_type": "sea",
            "trait": "superior_tactician"
        },
        {
            "name": "Suresh Chakraborty",
            "skill": 0,
            "force_type": "sea",
            "trait": "superior_tactician"
        },
        {
            "name": "Shishira Farooqi",
            "skill": 0,
            "force_type": "sea",
            "trait": "common"
        },
        {
            "name": "Navin Poonia",
            "skill": 0,
            "force_type": "sea",
            "trait": "superior_tactician"
        },
        {
            "name": "Nihal Joshi",
            "skill": 0,
            "force_type": "sea",
            "trait": "common"
        },
        {
            "name": "Bhavesh Khan",
            "skill": 0,
            "force_type": "sea",
            "trait": "spotter"
        },
        {
            "name": "Shridhar Iyer",
            "skill": 0,
            "force_type": "sea",
            "trait": "common"
        },
        {
            "name": "Dinesh Jain",
            "skill": 0,
            "force_type": "sea",
            "trait": "superior_tactician"
        },
        {
            "name": "Ekram Patel",
            "skill": 0,
            "force_type": "sea",
            "trait": "common"
        },
        {
            "name": "Adesh Bisht",
            "skill": 0,
            "force_type": "sea",
            "trait": "common"
        },
        {
            "name": "Anup Parmar",
            "skill": 0,
            "force_type": "sea",
            "trait": "superior_tactician"
        },
        {
            "name": "Bhushan Sehgal",
            "skill": 0,
            "force_type": "sea",
            "trait": "common"
        },
        {
            "name": "Krishnayya Nayak",
            "skill": 0,
            "force_type": "sea",
            "trait": "spotter"
        },
        {
            "name": "Nirav Rathore",
            "skill": 0,
            "force_type": "sea",
            "trait": "common"
        },
        {
            "name": "Sandeep Fernandes",
            "skill": 0,
            "force_type": "sea",
            "trait": "common"
        },
        {
            "name": "Vinod Rana",
            "skill": 0,
            "force_type": "sea",
            "trait": "common"
        },
        {
            "name": "Dinesh Jain",
            "skill": 0,
            "force_type": "sea",
            "trait": "superior_tactician"
        },
        {
            "name": "Jaipal Bhosle",
            "skill": 0,
            "force_type": "sea",
            "trait": "superior_tactician"
        },
        {
            "name": "Bhushan Poonia",
            "skill": 0,
            "force_type": "sea",
            "trait": "common"
        },
        {
            "name": "Ekram Yada",
            "skill": 0,
            "force_type": "sea",
            "trait": "common"
        },
        {
            "name": "Sukhbir Ali",
            "skill": 0,
            "force_type": "sea",
            "trait": "common"
        },
        {
            "name": "Amit Iyer",
            "skill": 0,
            "force_type": "sea",
            "trait": "common"
        },
        {
            "name": "Abhishek Parab",
            "skill": 0,
            "force_type": "sea",
            "trait": "common"
        },
        {
            "name": "Ira Singhal",
            "skill": 0,
            "force_type": "sea",
            "trait": "superior_tactician"
        },
        {
            "name": "Rakesh Kothari",
            "skill": 0,
            "force_type": "sea",
            "trait": "common"
        },
        {
            "name": "Harsh Srinivas",
            "skill": 0,
            "force_type": "sea",
            "trait": "seawolf"
        },
        {
            "name": "Anurag Somani",
            "skill": 0,
            "force_type": "sea",
            "trait": "common"
        },
        {
            "name": "Ravi Parmar",
            "skill": 0,
            "force_type": "sea",
            "trait": "common"
        },
        {
            "name": "Bappaditya Rathore",
            "skill": 0,
            "force_type": "sea",
            "trait": "common"
        },
        {
            "name": "Bappaditya Inamdar",
            "skill": 0,
            "force_type": "sea",
            "trait": "common"
        },
        {
            "name": "Aseem Pradhan",
            "skill": 0,
            "force_type": "sea",
            "trait": "common"
        },
        {
            "name": "Abhishek Deshmukh",
            "skill": 0,
            "force_type": "air",
            "trait": "common"
        },
        {
            "name": "Keyur Gounder",
            "skill": 0,
            "force_type": "air",
            "trait": "common"
        },
        {
            "name": "Bhavesh Kashyap",
            "skill": 0,
            "force_type": "air",
            "trait": "common"
        },
        {
            "name": "Bappaditya Srinivas",
            "skill": 0,
            "force_type": "air",
            "trait": "tank_buster"
        },
        {
            "name": "Wasim Ganguly",
            "skill": 0,
            "force_type": "air",
            "trait": "superior_air_tactician"
        },
        {
            "name": "Ekram Rana",
            "skill": 0,
            "force_type": "air",
            "trait": "common"
        },
        {
            "name": "Kartika Amin",
            "skill": 0,
            "force_type": "air",
            "trait": "common"
        },
        {
            "name": "Yoges Baghel",
            "skill": 0,
            "force_type": "air",
            "trait": "common"
        },
        {
            "name": "Vinay Dravid",
            "skill": 0,
            "force_type": "air",
            "trait": "common"
        },
        {
            "name": "Krishnan Gowda",
            "skill": 0,
            "force_type": "air",
            "trait": "common"
        },
        {
            "name": "Gotama Jain",
            "skill": 0,
            "force_type": "air",
            "trait": "common"
        },
        {
            "name": "Karthik Mishra",
            "skill": 0,
            "force_type": "air",
            "trait": "common"
        },
        {
            "name": "Sandeep Reddy",
            "skill": 0,
            "force_type": "air",
            "trait": "fleet_destroyer"
        },
        {
            "name": "Ammar Kulkarni",
            "skill": 0,
            "force_type": "air",
            "trait": "common"
        },
        {
            "name": "Mahesh Holkar",
            "skill": 0,
            "force_type": "air",
            "trait": "superior_air_tactician"
        },
        {
            "name": "Vikas Dutt",
            "skill": 0,
            "force_type": "air",
            "trait": "superior_air_tactician"
        },
        {
            "name": "Yoges Poonia",
            "skill": 0,
            "force_type": "air",
            "trait": "common"
        },
        {
            "name": "Ritwik Parashar",
            "skill": 0,
            "force_type": "air",
            "trait": "common"
        },
        {
            "name": "Jagannath Ray",
            "skill": 0,
            "force_type": "air",
            "trait": "common"
        },
        {
            "name": "Bharat Chatterjee",
            "skill": 0,
            "force_type": "air",
            "trait": "superior_air_tactician"
        },
        {
            "name": "Kiran Arora",
            "skill": 0,
            "force_type": "air",
            "trait": "superior_air_tactician"
        },
        {
            "name": "Rakesh Mewati",
            "skill": 0,
            "force_type": "air",
            "trait": "common"
        },
        {
            "name": "Nilesh Amin",
            "skill": 0,
            "force_type": "air",
            "trait": "superior_air_tactician"
        },
        {
            "name": "Vinay Somani",
            "skill": 0,
            "force_type": "air",
            "trait": "common"
        },
        {
            "name": "Harsh Somani",
            "skill": 0,
            "force_type": "air",
            "trait": "common"
        },
        {
            "name": "Dipankar Poonia",
            "skill": 0,
            "force_type": "air",
            "trait": "common"
        },
        {
            "name": "Karthik Parab",
            "skill": 0,
            "force_type": "air",
            "trait": "common"
        },
        {
            "name": "Shishir Rizvi",
            "skill": 0,
            "force_type": "air",
            "trait": "common"
        },
        {
            "name": "Sunil Nayak",
            "skill": 0,
            "force_type": "air",
            "trait": "superior_air_tactician"
        },
        {
            "name": "Amit Ganguly",
            "skill": 0,
            "force_type": "air",
            "trait": "superior_air_tactician"
        },
        {
            "name": "Munish Dravid",
            "skill": 0,
            "force_type": "air",
            "trait": "carpet_bomber"
        },
        {
            "name": "Akhil Roy",
            "skill": 0,
            "force_type": "air",
            "trait": "common"
        },
        {
            "name": "Ajay Singh",
            "skill": 0,
            "force_type": "air",
            "trait": "common"
        },
        {
            "name": "Jaipal Rawat",
            "skill": 0,
            "force_type": "air",
            "trait": "superior_air_tactician"
        },
        {
            "name": "Yoges Bhatt",
            "skill": 0,
            "force_type": "air",
            "trait": "common"
        }
    ]
}