{
    "country": "NGK",
    "leaders": [
        {
            "name": "Krikor Sargsyan",
            "skill": 0,
            "force_type": "land",
            "trait": "common"
        },
        {
            "name": "Artyom Khachatryan",
            "skill": 0,
            "force_type": "land",
            "trait": "common"
        },
        {
            "name": "Areg Harutyunyan",
            "skill": 0,
            "force_type": "land",
            "trait": "common"
        },
        {
            "name": "Varuzhan Hovhannisyan",
            "skill": 0,
            "force_type": "land",
            "trait": "common"
        },
        {
            "name": "Aghvan Sargsyan",
            "skill": 0,
            "force_type": "land",
            "trait": "commando"
        },
        {
            "name": "Ari Harutyunyan",
            "skill": 0,
            "force_type": "land",
            "trait": "common"
        },
        {
            "name": "Karen Sargsyan",
            "skill": 0,
            "force_type": "land",
            "trait": "common"
        },
        {
            "name": "Karen Khachatryan",
            "skill": 0,
            "force_type": "land",
            "trait": "defensive_doctrine"
        },
        {
            "name": "Arshavir Khachatryan",
            "skill": 0,
            "force_type": "land",
            "trait": "common"
        },
        {
            "name": "Sevag Hovhannisyan",
            "skill": 0,
            "force_type": "land",
            "trait": "common"
        },
        {
            "name": "Arshavir Harutyunyan",
            "skill": 0,
            "force_type": "land",
            "trait": "common"
        },
        {
            "name": "Karen Harutyunyan",
            "skill": 0,
            "force_type": "land",
            "trait": "common"
        },
        {
            "name": "Varuzhan Hovhannisyan",
            "skill": 0,
            "force_type": "land",
            "trait": "common"
        },
        {
            "name": "Hrant Harutyunyan",
            "skill": 0,
            "force_type": "land",
            "trait": "common"
        },
        {
            "name": "Ari Harutyunyan",
            "skill": 0,
            "force_type": "land",
            "trait": "common"
        },
        {
            "name": "Hrant Khachatryan",
            "skill": 0,
            "force_type": "land",
            "trait": "common"
        },
        {
            "name": "Hovhannes Khachatryan",
            "skill": 0,
            "force_type": "land",
            "trait": "logistics_wizard"
        },
        {
            "name": "Vartan Grigorya",
            "skill": 0,
            "force_type": "land",
            "trait": "common"
        },
        {
            "name": "Arshavir Khachatryan",
            "skill": 0,
            "force_type": "land",
            "trait": "offensive_doctrine"
        },
        {
            "name": "Hrant Sargsyan",
            "skill": 0,
            "force_type": "land",
            "trait": "commando"
        },
        {
            "name": "Karen Khachatryan",
            "skill": 0,
            "force_type": "land",
            "trait": "common"
        },
        {
            "name": "Aram Grigorya",
            "skill": 0,
            "force_type": "land",
            "trait": "common"
        },
        {
            "name": "Hovhannes Hovhannisyan",
            "skill": 0,
            "force_type": "land",
            "trait": "common"
        },
        {
            "name": "Hrant Grigorya",
            "skill": 0,
            "force_type": "land",
            "trait": "common"
        },
        {
            "name": "Vahagn Harutyunyan",
            "skill": 0,
            "force_type": "land",
            "trait": "common"
        },
        {
            "name": "Hrant Harutyunyan",
            "skill": 0,
            "force_type": "land",
            "trait": "common"
        },
        {
            "name": "Hovhannes Sargsyan",
            "skill": 0,
            "force_type": "land",
            "trait": "common"
        },
        {
            "name": "Karen Hovhannisyan",
            "skill": 0,
            "force_type": "land",
            "trait": "common"
        },
        {
            "name": "Vartan Harutyunyan",
            "skill": 0,
            "force_type": "land",
            "trait": "common"
        },
        {
            "name": "Ari Khachatryan",
            "skill": 0,
            "force_type": "land",
            "trait": "common"
        },
        {
            "name": "Garo Grigorya",
            "skill": 0,
            "force_type": "land",
            "trait": "common"
        },
        {
            "name": "Ari Hovhannisyan",
            "skill": 0,
            "force_type": "land",
            "trait": "common"
        },
        {
            "name": "Mkrtich Hovhannisyan",
            "skill": 0,
            "force_type": "land",
            "trait": "common"
        },
        {
            "name": "Vahagn Harutyunyan",
            "skill": 0,
            "force_type": "land",
            "trait": "common"
        },
        {
            "name": "Hrant Khachatryan",
            "skill": 0,
            "force_type": "land",
            "trait": "panzer_leader"
        },
        {
            "name": "Ari Hovhannisyan",
            "skill": 0,
            "force_type": "land",
            "trait": "common"
        },
        {
            "name": "Karen Grigorya",
            "skill": 0,
            "force_type": "land",
            "trait": "commando"
        },
        {
            "name": "Vartan Hovhannisyan",
            "skill": 0,
            "force_type": "land",
            "trait": "common"
        },
        {
            "name": "Areg Khachatryan",
            "skill": 0,
            "force_type": "land",
            "trait": "common"
        },
        {
            "name": "Garo Harutyunyan",
            "skill": 0,
            "force_type": "land",
            "trait": "common"
        },
        {
            "name": "Sevag Sargsyan",
            "skill": 0,
            "force_type": "land",
            "trait": "common"
        },
        {
            "name": "Arshavir Sargsyan",
            "skill": 0,
            "force_type": "land",
            "trait": "common"
        },
        {
            "name": "Sevag Grigorya",
            "skill": 0,
            "force_type": "land",
            "trait": "common"
        },
        {
            "name": "Sevag Hovhannisyan",
            "skill": 0,
            "force_type": "land",
            "trait": "commando"
        },
        {
            "name": "Arshavir Sargsyan",
            "skill": 0,
            "force_type": "land",
            "trait": "common"
        },
        {
            "name": "Garabed Khachatryan",
            "skill": 0,
            "force_type": "land",
            "trait": "common"
        },
        {
            "name": "Karen Grigorya",
            "skill": 0,
            "force_type": "land",
            "trait": "common"
        },
        {
            "name": "Mkrtich Harutyunyan",
            "skill": 0,
            "force_type": "land",
            "trait": "common"
        },
        {
            "name": "Vartan Sargsyan",
            "skill": 0,
            "force_type": "land",
            "trait": "defensive_doctrine"
        },
        {
            "name": "Karen Sargsyan",
            "skill": 0,
            "force_type": "land",
            "trait": "common"
        },
        {
            "name": "Areg Harutyunyan",
            "skill": 0,
            "force_type": "land",
            "trait": "common"
        },
        {
            "name": "Vige Sargsyan",
            "skill": 0,
            "force_type": "sea",
            "trait": "superior_tactician"
        },
        {
            "name": "Karen Harutyunyan",
            "skill": 0,
            "force_type": "sea",
            "trait": "common"
        },
        {
            "name": "Mkrtich Khachatryan",
            "skill": 0,
            "force_type": "sea",
            "trait": "common"
        },
        {
            "name": "Sevag Grigorya",
            "skill": 0,
            "force_type": "sea",
            "trait": "common"
        },
        {
            "name": "Vige Harutyunyan",
            "skill": 0,
            "force_type": "sea",
            "trait": "common"
        },
        {
            "name": "Hrant Grigorya",
            "skill": 0,
            "force_type": "sea",
            "trait": "common"
        },
        {
            "name": "Varuzhan Grigorya",
            "skill": 0,
            "force_type": "sea",
            "trait": "common"
        },
        {
            "name": "Areg Sargsyan",
            "skill": 0,
            "force_type": "sea",
            "trait": "seawolf"
        },
        {
            "name": "Mkrtich Khachatryan",
            "skill": 0,
            "force_type": "sea",
            "trait": "common"
        },
        {
            "name": "Arshavir Sargsyan",
            "skill": 0,
            "force_type": "sea",
            "trait": "seawolf"
        },
        {
            "name": "Karen Grigorya",
            "skill": 0,
            "force_type": "sea",
            "trait": "common"
        },
        {
            "name": "Vahagn Khachatryan",
            "skill": 0,
            "force_type": "sea",
            "trait": "common"
        },
        {
            "name": "Vige Hovhannisyan",
            "skill": 0,
            "force_type": "sea",
            "trait": "common"
        },
        {
            "name": "Hrant Sargsyan",
            "skill": 0,
            "force_type": "sea",
            "trait": "common"
        },
        {
            "name": "Areg Khachatryan",
            "skill": 0,
            "force_type": "sea",
            "trait": "common"
        },
        {
            "name": "Krikor Sargsyan",
            "skill": 0,
            "force_type": "sea",
            "trait": "superior_tactician"
        },
        {
            "name": "Hovhannes Harutyunyan",
            "skill": 0,
            "force_type": "sea",
            "trait": "superior_tactician"
        },
        {
            "name": "Garo Khachatryan",
            "skill": 0,
            "force_type": "sea",
            "trait": "common"
        },
        {
            "name": "Aghvan Sargsyan",
            "skill": 0,
            "force_type": "sea",
            "trait": "common"
        },
        {
            "name": "Artyom Khachatryan",
            "skill": 0,
            "force_type": "sea",
            "trait": "common"
        },
        {
            "name": "Garabed Hovhannisyan",
            "skill": 0,
            "force_type": "sea",
            "trait": "common"
        },
        {
            "name": "Garo Sargsyan",
            "skill": 0,
            "force_type": "sea",
            "trait": "common"
        },
        {
            "name": "Vige Grigorya",
            "skill": 0,
            "force_type": "sea",
            "trait": "common"
        },
        {
            "name": "Vartan Sargsyan",
            "skill": 0,
            "force_type": "sea",
            "trait": "common"
        },
        {
            "name": "Garo Grigorya",
            "skill": 0,
            "force_type": "sea",
            "trait": "common"
        },
        {
            "name": "Areg Harutyunyan",
            "skill": 0,
            "force_type": "sea",
            "trait": "common"
        },
        {
            "name": "Hagop Grigorya",
            "skill": 0,
            "force_type": "sea",
            "trait": "common"
        },
        {
            "name": "Karen Grigorya",
            "skill": 0,
            "force_type": "sea",
            "trait": "common"
        },
        {
            "name": "Arshavir Khachatryan",
            "skill": 0,
            "force_type": "sea",
            "trait": "blockade_runner"
        },
        {
            "name": "Mkrtich Khachatryan",
            "skill": 0,
            "force_type": "sea",
            "trait": "common"
        },
        {
            "name": "Vige Sargsyan",
            "skill": 0,
            "force_type": "sea",
            "trait": "common"
        },
        {
            "name": "Hovhannes Harutyunyan",
            "skill": 0,
            "force_type": "sea",
            "trait": "blockade_runner"
        },
        {
            "name": "Areg Khachatryan",
            "skill": 0,
            "force_type": "sea",
            "trait": "common"
        },
        {
            "name": "Garo Harutyunyan",
            "skill": 0,
            "force_type": "sea",
            "trait": "common"
        },
        {
            "name": "Artyom Hovhannisyan",
            "skill": 0,
            "force_type": "sea",
            "trait": "superior_tactician"
        },
        {
            "name": "Sevag Harutyunyan",
            "skill": 0,
            "force_type": "sea",
            "trait": "common"
        },
        {
            "name": "Krikor Grigorya",
            "skill": 0,
            "force_type": "sea",
            "trait": "superior_tactician"
        },
        {
            "name": "Vartan Khachatryan",
            "skill": 0,
            "force_type": "sea",
            "trait": "superior_tactician"
        },
        {
            "name": "Ari Hovhannisyan",
            "skill": 0,
            "force_type": "sea",
            "trait": "superior_tactician"
        },
        {
            "name": "Vahan Harutyunyan",
            "skill": 0,
            "force_type": "air",
            "trait": "common"
        },
        {
            "name": "Varuzhan Sargsyan",
            "skill": 0,
            "force_type": "air",
            "trait": "common"
        },
        {
            "name": "Vahagn Hovhannisyan",
            "skill": 0,
            "force_type": "air",
            "trait": "common"
        },
        {
            "name": "Areg Grigorya",
            "skill": 0,
            "force_type": "air",
            "trait": "night_flyer"
        },
        {
            "name": "Aram Hovhannisyan",
            "skill": 0,
            "force_type": "air",
            "trait": "fleet_destroyer"
        },
        {
            "name": "Mkrtich Hovhannisyan",
            "skill": 0,
            "force_type": "air",
            "trait": "superior_air_tactician"
        },
        {
            "name": "Karen Khachatryan",
            "skill": 0,
            "force_type": "air",
            "trait": "common"
        },
        {
            "name": "Ari Khachatryan",
            "skill": 0,
            "force_type": "air",
            "trait": "common"
        },
        {
            "name": "Vartan Khachatryan",
            "skill": 0,
            "force_type": "air",
            "trait": "common"
        },
        {
            "name": "Aghvan Sargsyan",
            "skill": 0,
            "force_type": "air",
            "trait": "common"
        },
        {
            "name": "Vahagn Grigorya",
            "skill": 0,
            "force_type": "air",
            "trait": "common"
        },
        {
            "name": "Vahagn Sargsyan",
            "skill": 0,
            "force_type": "air",
            "trait": "common"
        },
        {
            "name": "Vahan Khachatryan",
            "skill": 0,
            "force_type": "air",
            "trait": "common"
        },
        {
            "name": "Vige Harutyunyan",
            "skill": 0,
            "force_type": "air",
            "trait": "common"
        },
        {
            "name": "Vartan Khachatryan",
            "skill": 0,
            "force_type": "air",
            "trait": "common"
        },
        {
            "name": "Vartan Hovhannisyan",
            "skill": 0,
            "force_type": "air",
            "trait": "common"
        },
        {
            "name": "Vahagn Hovhannisyan",
            "skill": 0,
            "force_type": "air",
            "trait": "superior_air_tactician"
        },
        {
            "name": "Garabed Harutyunyan",
            "skill": 0,
            "force_type": "air",
            "trait": "night_flyer"
        },
        {
            "name": "Vartan Hovhannisyan",
            "skill": 0,
            "force_type": "air",
            "trait": "common"
        },
        {
            "name": "Arshavir Sargsyan",
            "skill": 0,
            "force_type": "air",
            "trait": "common"
        },
        {
            "name": "Vartan Sargsyan",
            "skill": 0,
            "force_type": "air",
            "trait": "night_flyer"
        },
        {
            "name": "Areg Harutyunyan",
            "skill": 0,
            "force_type": "air",
            "trait": "superior_air_tactician"
        },
        {
            "name": "Varuzhan Grigorya",
            "skill": 0,
            "force_type": "air",
            "trait": "common"
        },
        {
            "name": "Garabed Grigorya",
            "skill": 0,
            "force_type": "air",
            "trait": "common"
        },
        {
            "name": "Sevag Hovhannisyan",
            "skill": 0,
            "force_type": "air",
            "trait": "common"
        },
        {
            "name": "Hagop Harutyunyan",
            "skill": 0,
            "force_type": "air",
            "trait": "common"
        },
        {
            "name": "Sevag Grigorya",
            "skill": 0,
            "force_type": "air",
            "trait": "common"
        },
        {
            "name": "Artyom Khachatryan",
            "skill": 0,
            "force_type": "air",
            "trait": "common"
        },
        {
            "name": "Hagop Harutyunyan",
            "skill": 0,
            "force_type": "air",
            "trait": "common"
        },
        {
            "name": "Artyom Hovhannisyan",
            "skill": 0,
            "force_type": "air",
            "trait": "common"
        },
        {
            "name": "Krikor Sargsyan",
            "skill": 0,
            "force_type": "air",
            "trait": "common"
        },
        {
            "name": "Arshavir Harutyunyan",
            "skill": 0,
            "force_type": "air",
            "trait": "common"
        },
        {
            "name": "Hrant Grigorya",
            "skill": 0,
            "force_type": "air",
            "trait": "common"
        },
        {
            "name": "Mkrtich Sargsyan",
            "skill": 0,
            "force_type": "air",
            "trait": "superior_air_tactician"
        },
        {
            "name": "Garo Khachatryan",
            "skill": 0,
            "force_type": "air",
            "trait": "common"
        },
        {
            "name": "Mkrtich Grigorya",
            "skill": 0,
            "force_type": "air",
            "trait": "common"
        },
        {
            "name": "Areg Harutyunyan",
            "skill": 0,
            "force_type": "air",
            "trait": "common"
        },
        {
            "name": "Aghvan Harutyunyan",
            "skill": 0,
            "force_type": "air",
            "trait": "fleet_destroyer"
        },
        {
            "name": "Aram Khachatryan",
            "skill": 0,
            "force_type": "air",
            "trait": "common"
        },
        {
            "name": "Garabed Khachatryan",
            "skill": 0,
            "force_type": "air",
            "trait": "superior_air_tactician"
        }
    ]
}