{
    "owner": "CHI",
    "controller": "CHI",
    "add_core": [
        "SIK",
        "CHI",
        "CHC"
    ],
    "population_total": {
        "amount": 731,
        "template": 6,
        "populations": {
            "farmers": 0.44021,
            "labourers": 0.4402,
            "craftsmen": 0.0,
            "clerks": 0.0,
            "aristocrats": 0.00414,
            "artisans": 0.03347,
            "bureaucrats": 0.00432,
            "capitalists": 0.03199,
            "clergymen": 0.01775,
            "officers": 0.00592,
            "slaves": 0.0,
            "soldiers": 0.022
        },
        "cultures": {
            "uighur": 0.89928,
            "hui": 0.10072
        },
        "religions": {
            "sunni": 1.0
        }
    },
    "buildings": [
        {
            "name": "railway",
            "size": 2
        }
    ],
    "terrain": "arctic"
}