{
    "owner": "CAN",
    "controller": "CAN",
    "add_core": "CAN",
    "population_total": {
        "amount": 2807,
        "template": 92,
        "populations": {
            "farmers": 0.80582,
            "labourers": 0.069,
            "craftsmen": 0.0,
            "clerks": 0.0,
            "aristocrats": 0.0041,
            "artisans": 0.03355,
            "bureaucrats": 0.00439,
            "capitalists": 0.03606,
            "clergymen": 0.0173,
            "officers": 0.00538,
            "slaves": 0.0,
            "soldiers": 0.0244
        },
        "cultures": {
            "anglo_canadian": 0.39775,
            "metis": 0.60225
        },
        "religions": {
            "protestant": 0.33869,
            "atheist": 0.15066,
            "catholic": 0.48212,
            "animist": 0.02853
        }
    },
    "good": "grain",
    "buildings": [
        {
            "name": "railway",
            "size": 2
        }
    ],
    "terrain": "forest"
}